analyzer/__init__.py
analyzer/analyzer.py
analyzer/code_collector.py
analyzer/connector.py
analyzer/decorator_updater.py
analyzer/helper.py
analyzer/s3_connector.py
analyzer/testItem.py
analyzer/testRunConfig.py
analyzer/testomat_item.py
analyzer/testomatio.py
tests/sub/__init__.py
tests/sub/test_class_sub.py
tests/sub/test_sub.py
tests/sub/sub_mob/__init__.py
tests/sub/sub_mob/sub_sub_class_test.py
tests/sub/sub_mob/sub_sub_test.py
pytest_analyzer-1.6.0.dist-info/LICENSE
pytest_analyzer-1.6.0.dist-info/METADATA
pytest_analyzer-1.6.0.dist-info/WHEEL
pytest_analyzer-1.6.0.dist-info/entry_points.txt
pytest_analyzer-1.6.0.dist-info/top_level.txt
pytest_analyzer-1.6.0.dist-info/RECORD
