Metadata-Version: 2.1
Name: pytest-analyzer
Version: 1.6.0
Summary: this plugin allows to analyze tests in pytest project, collect test metadata and sync it with testomat.io TCM system
Author: Oleksii Ostapov
Project-URL: Author's Blog, https://qamania.org
Project-URL: Homepage, https://github.com/Ypurek/pytest-analyzer
Project-URL: Bug Tracker, https://github.com/Ypurek/pytest-analyzer/issues
Classifier: Framework :: Pytest
Classifier: Programming Language :: Python :: 3
Classifier: License :: OSI Approved :: MIT License
Classifier: Operating System :: OS Independent
Requires-Python: >=3.10
License-File: LICENSE
Requires-Dist: requests >=2.29.0
Requires-Dist: pytest <8.0.0,>=7.3.1
Requires-Dist: boto3 >=1.28.28
Requires-Dist: libcst ==1.1.0
